setup.py
platformer/__init__.py
platformer/cli/__init__.py
platformer/cli/code.py
platformer/cli/deploy.py
platformer/cli/oneclick.py
platformer/cli/test.py
platformer/core/__init__.py
platformer/core/parser.py
platformer/core/coders/__init__.py
platformer/core/coders/terraform.py
platformer/core/coders/yaml.py
platformer/core/deployers/__init__.py
platformer/core/deployers/azdo.py
platformer/core/deployers/github.py
platformer/core/deployers/local.py
platformer/core/testers/__init__.py
platformer/modules/__init__.py
platformer/templates/__init__.py
platformer/templates/base_terraform.py
platformer_iac.egg-info/PKG-INFO
platformer_iac.egg-info/SOURCES.txt
platformer_iac.egg-info/dependency_links.txt
platformer_iac.egg-info/entry_points.txt
platformer_iac.egg-info/requires.txt
platformer_iac.egg-info/top_level.txt